csvpeek/__init__.py
csvpeek/csvpeek.py
csvpeek/duck.py
csvpeek/filters.py
csvpeek/main.py
csvpeek/selection_utils.py
csvpeek/ui.py
csvpeek-0.10.1.dist-info/METADATA
csvpeek-0.10.1.dist-info/WHEEL
csvpeek-0.10.1.dist-info/entry_points.txt
csvpeek-0.10.1.dist-info/licenses/LICENSE
csvpeek-0.10.1.dist-info/RECORD
