Metadata-Version: 2.4
Name: csvpeek
Version: 0.10.1
Summary: A snappy CSV viewer TUI - peek at your data fast
Project-URL: Homepage, https://github.com/giantatwork/csvpeek
Project-URL: Repository, https://github.com/giantatwork/csvpeek
Project-URL: Issues, https://github.com/giantatwork/csvpeek/issues
Author-email: Giant at Work <info@giantatwork.nl>
License: MIT
License-File: LICENSE
Keywords: csv,data,duckdb,terminal,tui,urwid,viewer
Classifier: Development Status :: 4 - Beta
Classifier: Environment :: Console
Classifier: Intended Audience :: Developers
Classifier: Intended Audience :: Science/Research
Classifier: License :: OSI Approved :: MIT License
Classifier: Operating System :: OS Independent
Classifier: Programming Language :: Python :: 3
Classifier: Programming Language :: Python :: 3.12
Classifier: Topic :: Software Development :: Libraries :: Python Modules
Classifier: Topic :: Terminals
Classifier: Topic :: Utilities
Requires-Python: >=3.12
Requires-Dist: duckdb>=1.1.0
Requires-Dist: pyperclip>=1.8.0
Requires-Dist: urwid>=2.1.0
